japandas/__init__.py
japandas/compat.py
japandas/version.py
japandas/core/__init__.py
japandas/core/strings.py
japandas/core/tests/__init__.py
japandas/core/tests/test_strings.py
japandas/io/__init__.py
japandas/io/data.py
japandas/io/estat.py
japandas/io/tests/__init__.py
japandas/io/tests/test_estat.py
japandas/tools/__init__.py
japandas/tools/plotting.py
japandas/tools/tests/__init__.py
japandas/tools/tests/test_plotting.py
japandas/tseries/__init__.py
japandas/tseries/holiday.py
japandas/tseries/tools.py
japandas/tseries/data/holidays.pkl
japandas/tseries/data/tseholidays.pkl
japandas/tseries/tests/__init__.py
japandas/tseries/tests/test_holiday.py
japandas/tseries/tests/test_tools.py
japandas-0.5.1.dist-info/DESCRIPTION.rst
japandas-0.5.1.dist-info/METADATA
japandas-0.5.1.dist-info/RECORD
japandas-0.5.1.dist-info/WHEEL
japandas-0.5.1.dist-info/metadata.json
japandas-0.5.1.dist-info/top_level.txt
