Metadata-Version: 2.0
Name: japandas
Version: 0.5.1
Summary: pandas japanese extension
Home-page: http://japandas.readthedocs.org/en/stable
Author: sinhrks
Author-email: sinhrks@gmail.com
License: BSD
Platform: UNKNOWN
Requires-Dist: pandas (>=0.20.0)
Requires-Dist: pandas-datareader (>=0.7.0)
